setup.py
circuikit/__init__.py
circuikit/protocols.py
circuikit.egg-info/PKG-INFO
circuikit.egg-info/SOURCES.txt
circuikit.egg-info/dependency_links.txt
circuikit.egg-info/requires.txt
circuikit.egg-info/top_level.txt
circuikit/main/__init__.py
circuikit/serial_monitor_interface/__init__.py
circuikit/serial_monitor_interface/chrome_process.py
circuikit/serial_monitor_interface/protocols.py
circuikit/serial_monitor_interface/serial_monitor_interface.py
circuikit/serial_monitor_interface/thinkercad.py
circuikit/serial_monitor_interface/types.py
circuikit/services/__init__.py
circuikit/services/file_logger.py
circuikit/services/service.py
circuikit/services/service_adapter.py
circuikit/services/thingsboard_gateway.py
examples/__init__.py
examples/app.py
examples/thinkercad_to_custom_ui/__init__.py
examples/thinkercad_to_custom_ui/example.py
examples/thinkercad_to_custom_ui/example_gui.py
examples/thinkercad_to_custom_ui/models.py