Metadata-Version: 2.1
Name: circuikit
Version: 0.1.0
Summary: A versatile tool for Arduino serial monitoring and interaction
Author: Shachar Tal
Author-email: stalmail10@gmail.com
Requires-Dist: anyio==4.4.0
Requires-Dist: attrs==23.2.0
Requires-Dist: black==24.4.2
Requires-Dist: certifi==2024.6.2
Requires-Dist: charset-normalizer==3.3.2
Requires-Dist: click==8.1.7
Requires-Dist: h11==0.14.0
Requires-Dist: httpcore==1.0.5
Requires-Dist: idna==3.7
Requires-Dist: mypy-extensions==1.0.0
Requires-Dist: outcome==1.3.0.post0
Requires-Dist: packaging==24.1
Requires-Dist: pathspec==0.12.1
Requires-Dist: platformdirs==4.2.2
Requires-Dist: PySocks==1.7.1
Requires-Dist: requests==2.32.3
Requires-Dist: selenium==4.21.0
Requires-Dist: sniffio==1.3.1
Requires-Dist: sortedcontainers==2.4.0
Requires-Dist: trio==0.25.1
Requires-Dist: trio-websocket==0.11.1
Requires-Dist: typing_extensions==4.12.2
Requires-Dist: urllib3==2.2.2
Requires-Dist: wsproto==1.2.0
